jobmon/server/__init__.py
jobmon/server/cli.py
jobmon/server/py.typed
jobmon/server/web/__init__.py
jobmon/server/web/_compat.py
jobmon/server/web/api.py
jobmon/server/web/app_factory.py
jobmon/server/web/hooks_and_handlers.py
jobmon/server/web/log_config.py
jobmon/server/web/server_side_exception.py
jobmon/server/web/wsgi.py
jobmon/server/web/models/__init__.py
jobmon/server/web/models/arg.py
jobmon/server/web/models/arg_type.py
jobmon/server/web/models/array.py
jobmon/server/web/models/cluster.py
jobmon/server/web/models/cluster_type.py
jobmon/server/web/models/dag.py
jobmon/server/web/models/edge.py
jobmon/server/web/models/node.py
jobmon/server/web/models/node_arg.py
jobmon/server/web/models/queue.py
jobmon/server/web/models/task.py
jobmon/server/web/models/task_arg.py
jobmon/server/web/models/task_attribute.py
jobmon/server/web/models/task_attribute_type.py
jobmon/server/web/models/task_instance.py
jobmon/server/web/models/task_instance_error_log.py
jobmon/server/web/models/task_instance_status.py
jobmon/server/web/models/task_resources.py
jobmon/server/web/models/task_resources_type.py
jobmon/server/web/models/task_status.py
jobmon/server/web/models/task_template.py
jobmon/server/web/models/task_template_version.py
jobmon/server/web/models/template_arg_map.py
jobmon/server/web/models/tool.py
jobmon/server/web/models/tool_version.py
jobmon/server/web/models/workflow.py
jobmon/server/web/models/workflow_attribute.py
jobmon/server/web/models/workflow_attribute_type.py
jobmon/server/web/models/workflow_run.py
jobmon/server/web/models/workflow_run_status.py
jobmon/server/web/models/workflow_status.py
jobmon/server/web/routes/__init__.py
jobmon/server/web/routes/cli/__init__.py
jobmon/server/web/routes/cli/array.py
jobmon/server/web/routes/cli/task.py
jobmon/server/web/routes/cli/task_template.py
jobmon/server/web/routes/cli/workflow.py
jobmon/server/web/routes/fsm/__init__.py
jobmon/server/web/routes/fsm/array.py
jobmon/server/web/routes/fsm/cluster.py
jobmon_server-3.2.2.dist-info/METADATA
jobmon_server-3.2.2.dist-info/WHEEL
jobmon_server-3.2.2.dist-info/entry_points.txt
jobmon_server-3.2.2.dist-info/top_level.txt
jobmon_server-3.2.2.dist-info/RECORD
