Metadata-Version: 2.1
Name: jobmon-server
Version: 3.2.2
Summary: Web Service and Model for Jobmon
Classifier: Programming Language :: Python :: 3.9
Classifier: Programming Language :: Python :: 3.8
Classifier: Programming Language :: Python :: 3.7
Requires-Python: >=3.7
Requires-Dist: jobmon-core (==3.2.2)
Requires-Dist: flask
Requires-Dist: flask-cors
Requires-Dist: elastic-apm[flask]
Requires-Dist: pymysql
Requires-Dist: sqlalchemy
Requires-Dist: sqlalchemy-utils
Requires-Dist: structlog
Requires-Dist: scipy
Requires-Dist: pandas
Requires-Dist: polars
